analyticlab/__init__.py
analyticlab/amath.py
analyticlab/const.py
analyticlab/latexoutput.py
analyticlab/lsym.py
analyticlab/lsymitem.py
analyticlab/num.py
analyticlab/numitem.py
analyticlab/outlier.py
analyticlab/twoitems.py
analyticlab/lookup/DixonTable.py
analyticlab/lookup/FTable.py
analyticlab/lookup/GrubbsTable.py
analyticlab/lookup/NairTable.py
analyticlab/lookup/Physics_tTable.py
analyticlab/lookup/RangeTable.py
analyticlab/lookup/SkewKuriTable.py
analyticlab/lookup/__init__.py
analyticlab/lookup/alphaToConf.py
analyticlab/lookup/tTable.py
analyticlab/measure/ACategory.py
analyticlab/measure/BCategory.py
analyticlab/measure/__init__.py
analyticlab/measure/basemeasure.py
analyticlab/measure/ins.py
analyticlab/measure/measure.py
analyticlab/measure/std.py
analyticlab/system/__init__.py
analyticlab/system/exceptions.py
analyticlab/system/format_units.py
analyticlab/system/numberformat.py
analyticlab/system/statformat.py
analyticlab/system/text_unicode.py
analyticlab/system/unit_open.py
analyticlab-0.3.2.dist-info/METADATA
analyticlab-0.3.2.dist-info/RECORD
analyticlab-0.3.2.dist-info/WHEEL
analyticlab-0.3.2.dist-info/top_level.txt
