Metadata-Version: 2.1
Name: analyticlab
Version: 0.3.2
Summary: A library for experimental data calculation, treatment and display, which can be used for College Physics Experiment, Analytical Chemistry, etc.
Home-page: https://github.com/xingrongtech/analyticlab
Author: xingrongtech
Author-email: wzv100@163.com
License: MIT License
Keywords: calculation,analysis,measure,uncertainty>=0.12.1,display
Platform: UNKNOWN
Classifier: Development Status :: 4 - Beta
Classifier: Operating System :: OS Independent
Classifier: Intended Audience :: Developers
Classifier: License :: OSI Approved :: BSD License
Classifier: Programming Language :: Python
Classifier: Programming Language :: Python :: Implementation
Classifier: Programming Language :: Python :: 3.4
Classifier: Programming Language :: Python :: 3.5
Classifier: Programming Language :: Python :: 3.6
Classifier: Topic :: Software Development :: Libraries
Requires-Dist: numpy
Requires-Dist: scipy
Requires-Dist: sympy
Requires-Dist: quantities
